cvedb/__init__.py
cvedb/__main__.py
cvedb/cli.py
cvedb/cpe.py
cvedb/cve.py
cvedb/db.py
cvedb/feed.py
cvedb/nvd.py
cvedb/printing.py
cvedb/schemas.py
cvedb/search.py
cvedb/sql.py
cvedb/data/nvdcve-1.1-2002.json.gz
cvedb/data/nvdcve-1.1-2002.meta
cvedb/data/nvdcve-1.1-2003.json.gz
cvedb/data/nvdcve-1.1-2003.meta
cvedb/data/nvdcve-1.1-2004.json.gz
cvedb/data/nvdcve-1.1-2004.meta
cvedb/data/nvdcve-1.1-2005.json.gz
cvedb/data/nvdcve-1.1-2005.meta
cvedb/data/nvdcve-1.1-2006.json.gz
cvedb/data/nvdcve-1.1-2006.meta
cvedb/data/nvdcve-1.1-2007.json.gz
cvedb/data/nvdcve-1.1-2007.meta
cvedb/data/nvdcve-1.1-2008.json.gz
cvedb/data/nvdcve-1.1-2008.meta
cvedb/data/nvdcve-1.1-2009.json.gz
cvedb/data/nvdcve-1.1-2009.meta
cvedb/data/nvdcve-1.1-2010.json.gz
cvedb/data/nvdcve-1.1-2010.meta
cvedb/data/nvdcve-1.1-2011.json.gz
cvedb/data/nvdcve-1.1-2011.meta
cvedb/data/nvdcve-1.1-2012.json.gz
cvedb/data/nvdcve-1.1-2012.meta
cvedb/data/nvdcve-1.1-2013.json.gz
cvedb/data/nvdcve-1.1-2013.meta
cvedb/data/nvdcve-1.1-2014.json.gz
cvedb/data/nvdcve-1.1-2014.meta
cvedb/data/nvdcve-1.1-2015.json.gz
cvedb/data/nvdcve-1.1-2015.meta
cvedb/data/nvdcve-1.1-2016.json.gz
cvedb/data/nvdcve-1.1-2016.meta
cvedb/data/nvdcve-1.1-2017.json.gz
cvedb/data/nvdcve-1.1-2017.meta
cvedb/data/nvdcve-1.1-2018.json.gz
cvedb/data/nvdcve-1.1-2018.meta
cvedb/data/nvdcve-1.1-2019.json.gz
cvedb/data/nvdcve-1.1-2019.meta
cvedb/data/nvdcve-1.1-2020.json.gz
cvedb/data/nvdcve-1.1-2020.meta
cvedb/data/nvdcve-1.1-2021.json.gz
cvedb/data/nvdcve-1.1-2021.meta
cvedb-0.0.5.dist-info/LICENSE
cvedb-0.0.5.dist-info/METADATA
cvedb-0.0.5.dist-info/WHEEL
cvedb-0.0.5.dist-info/entry_points.txt
cvedb-0.0.5.dist-info/top_level.txt
cvedb-0.0.5.dist-info/RECORD
