Metadata-Version: 2.1
Name: cvedb
Version: 0.0.5
Summary: Yet another CVE database
Home-page: https://github.com/trailofbits/cvedb
Author: Trail of Bits
License: LGPL-3.0-or-later
Platform: UNKNOWN
Classifier: Development Status :: 4 - Beta
Classifier: Environment :: Console
Classifier: Intended Audience :: Science/Research
Classifier: License :: OSI Approved :: GNU Lesser General Public License v3 or later (LGPLv3+)
Classifier: Programming Language :: Python :: 3 :: Only
Classifier: Topic :: Utilities
Requires-Python: >=3.6
Requires-Dist: cvss (>=2.2)
Requires-Dist: python-dateutil (>=2.8.1)
Requires-Dist: tqdm (>=4.48.0)
Requires-Dist: dataclasses ; python_version < "3.7"
Provides-Extra: dev
Requires-Dist: flake8 ; extra == 'dev'
Requires-Dist: pytest ; extra == 'dev'
Requires-Dist: rstr (~=2.2.6) ; extra == 'dev'
Requires-Dist: twine ; extra == 'dev'
